Workbook
Name Taper_rate: 'DCF Valuation '!$C$21
Name Tax_Rate: 'DCF Valuation '!$C$25
Name taxrate: '[1]DCF Modelling'!$C$26
Name UPDATE: 'Data Sheet'!$E$1

Sheet DCF Valuation 
B2: ITC LTD Financial Modelling
B4: Company Overview
B5: ITC Limited is one of India’s leading diversified conglomerates with a strong presence across multiple consumer and industrial businesses:
B7: FMCG – Cigarettes – Market leader in the Indian cigarette industry
B8: FMCG – Others – Foods (Aashirvaad, Sunfeast, Bingo), Personal Care (Fiama, Vivel), Agarbatti, Education & Stationery
B9: Hotels – Luxury, premium and mid-scale hospitality chain across India
B10: Paperboards, Paper & Packaging – Sustainable paper and packaging solutions
B11: Agri-Business – Integrated agri-value chain linking farmers to global markets
B12: Pan-India Presence with strong rural and urban reach
B13: Business Model: Strong brands, diversified portfolio, asset-light FMCG growth, focus on sustainability
B16: Key Assumptions & Methodology
B17: Parameter | C17: Value | D17: Rationale
B18: Valuation Date | C18: 14/12/2025
B19: Projection Period | C19: 5 Years | D19: From FY 26 to FY 30.
B20: Revenue Growth% | C20: 0.2 | D20: As per 1Q report of ITC for the FY26
B21: Annual Growth Tapering | C21: 0.02
B22: Terminal Growth Rate | C22: 0.06 | D22: Conervative loan term groeth considering India's GDP
B23: Risk-Free Rate (Rf) | C23: 0.065 | D23: As per India 10Y bond rate
B24: Equity Risk Premium (ERP) | C24: =12%-C23 -> 0.055 | D24: Expected return over risk free rate for equity investors
B25: Tax Rate | C25: 0.25
B26: Reinvestment | C26: 0.3 | D26: Assumption
B27: Pre-Tax Cost of Debt | C27: 0.08 | D27: Assumption
B30: Financial Performance (₹ Crores)
B31: INCOME STATEMENT
B32: Particulars | C32: 2021 | D32: =C32+1 -> 2022 | E32: =D32+1 -> 2023 | F32: =E32+1 -> 2024 | G32: =F32+1 -> 2025 | H32: CAGR
B33: Sales | C33: ='Data Sheet'!G17 -> 49257.45 | D33: ='Data Sheet'!H17 -> 60644.54 | E33: ='Data Sheet'!I17 -> 70919.03 | F33: ='Data Sheet'!J17 -> 67931.94 | G33: ='Data Sheet'!K17 -> 75323.34
B34: % growth | D34: =D33/C33 -> 1.231175 | E34: =E33/D33 -> 1.1694215 | F34: =F33/E33 -> 0.95788028 | G34: =G33/F33 -> 1.108806 | H34: =_xlfn.RRI(4,C33,G33) -> 0.11202464
B35: Cost of Goods Sold | C35: =SUM('Data Sheet'!G18,-'Data Sheet'!G19,'Data Sheet'!G20:G21) -> 22418.18 | D35: =SUM('Data Sheet'!H18,-'Data Sheet'!H19,'Data Sheet'!H20:H21) -> 29162.51 | E35: =SUM('Data Sheet'!I18,-'Data Sheet'!I19,'Data Sheet'!I20:I21) -> 32565.91 | F35: =SUM('Data Sheet'!J18,-'Data Sheet'!J19,'Data Sheet'!J20:J21) -> 30117.46 | G35: =SUM('Data Sheet'!K18,-'Data Sheet'!K19,'Data Sheet'!K20:K21) -> 35299.43
B36: % of revenue | C36: =C35/C33 -> 0.45512263 | D36: =D35/D33 -> 0.4808761 | E36: =E35/E33 -> 0.45919847 | F36: =F35/F33 -> 0.44334756 | G36: =G35/G33 -> 0.46863867
B37: Gross Profit | C37: =C33-C35 -> 26839.27 | D37: =D33-D35 -> 31482.03 | E37: =E33-E35 -> 38353.12 | F37: =F33-F35 -> 37814.48 | G37: =G33-G35 -> 40023.91
B38: % margin | C38: =C37/C33 -> 0.54487737 | D38: =D37/D33 -> 0.5191239 | E38: =E37/E33 -> 0.54080153 | F38: =F37/F33 -> 0.55665244 | G38: =G37/G33 -> 0.53136133
B39: Operating Expenses | C39: =SUM('Data Sheet'!G22:G24) -> 9774.49 | D39: =SUM('Data Sheet'!H22:H24) -> 10858.88 | E39: =SUM('Data Sheet'!I22:I24) -> 12648.86 | F39: =SUM('Data Sheet'!J22:J24) -> 12626.95 | G39: =SUM('Data Sheet'!K22:K24) -> 14184.46
B40: % of revenue | C40: =C39/C33 -> 0.19843678 | D40: =D39/D33 -> 0.17905783 | E40: =E39/E33 -> 0.17835636 | F40: =F39/F33 -> 0.18587648 | G40: =G39/G33 -> 0.18831427
B41: EBITDA | C41: =C37-C39 -> 17064.78 | D41: =D37-D39 -> 20623.15 | E41: =E37-E39 -> 25704.26 | F41: =F37-F39 -> 25187.53 | G41: =G37-G39 -> 25839.45
B42: % margin | C42: =C41/C33 -> 0.34644059 | D42: =D41/D33 -> 0.34006606 | E42: =E41/E33 -> 0.36244517 | F42: =F41/F33 -> 0.37077596 | G42: =G41/G33 -> 0.34304706
B43: Depreciation | C43: ='Data Sheet'!G26 -> 1645.59 | D43: ='Data Sheet'!H26 -> 1732.41 | E43: ='Data Sheet'!I26 -> 1809.01 | F43: ='Data Sheet'!J26 -> 1518.05 | G43: ='Data Sheet'!K26 -> 1646.32
B44: % of margin | C44: =C43/C33 -> 0.033407941 | D44: =D43/D33 -> 0.028566628 | E44: =E43/E33 -> 0.025508104 | F44: =F43/F33 -> 0.022346631 | G44: =G43/G33 -> 0.021856705
B45: EBIT | C45: =C41-C43 -> 15419.19 | D45: =D41-D43 -> 18890.74 | E45: =E41-E43 -> 23895.25 | F45: =F41-F43 -> 23669.48 | G45: =G41-G43 -> 24193.13
B46: % margin | C46: =C45/C33 -> 0.31303265 | D46: =D45/D33 -> 0.31149944 | E46: =E45/E33 -> 0.33693707 | F46: =F45/F33 -> 0.34842932 | G46: =G45/G33 -> 0.32119035
B47: Other Income | C47: ='Data Sheet'!G25 -> 2576.95 | D47: ='Data Sheet'!H25 -> 1909.72 | E47: ='Data Sheet'!I25 -> 2097.64 | F47: ='Data Sheet'!J25 -> 3330.45 | G47: ='Data Sheet'!K25 -> 17794.88
B48: Interest | C48: ='Data Sheet'!G27 -> 57.97 | D48: ='Data Sheet'!H27 -> 59.99 | E48: ='Data Sheet'!I27 -> 77.77 | F48: ='Data Sheet'!J27 -> 39.11 | G48: ='Data Sheet'!K27 -> 45.06
B49: % of debt | C49: =C48/'Data Sheet'!G59 -> 0.21404571 | D49: =D48/'Data Sheet'!H59 -> 0.24049872 | E49: =E48/'Data Sheet'!I59 -> 0.25411711 | F49: =F48/'Data Sheet'!J59 -> 0.12889299 | G49: =G48/'Data Sheet'!K59 -> 0.15836086
B50: Profit before tax | C50: =C45+C47-C48 -> 17938.17 | D50: =D45+D47-D48 -> 20740.47 | E50: =E45+E47-E48 -> 25915.12 | F50: =F45+F47-F48 -> 26960.82 | G50: =G45+G47-G48 -> 41942.95
B51: % of revenue | C51: =C50/C33 -> 0.36417171 | D51: =D50/D33 -> 0.34200062 | E51: =E50/E33 -> 0.36541842 | F51: =F50/F33 -> 0.39687988 | G51: =G50/G33 -> 0.55683869
B52: Tax | C52: ='Data Sheet'!G29 -> 4555.29 | D52: ='Data Sheet'!H29 -> 5237.34 | E52: ='Data Sheet'!I29 -> 6438.4 | F52: ='Data Sheet'!J29 -> 6209.46 | G52: ='Data Sheet'!K29 -> 6890.47
B53: % of PBT | C53: =C52/C50 -> 0.25394396 | D53: =D52/D50 -> 0.2525179 | E53: =E52/E50 -> 0.24844184 | F53: =F52/F50 -> 0.23031421 | G53: =G52/G50 -> 0.16428196
B54: Net profit | C54: =C50-C52 -> 13382.88 | D54: =D50-D52 -> 15503.13 | E54: =E50-E52 -> 19476.72 | F54: =F50-F52 -> 20751.36 | G54: =G50-G52 -> 35052.48
B55: % of revenue | C55: =C54/C33 -> 0.27169251 | D55: =D54/D33 -> 0.25563934 | E55: =E54/E33 -> 0.2746332 | F55: =F54/F33 -> 0.3054728 | G55: =G54/G33 -> 0.46536014
B57: BALANCE SHEET
B58: Particulars | C58: =C32 -> 2021 | D58: =D32 -> 2022 | E58: =E32 -> 2023 | F58: =F32 -> 2024 | G58: =G32 -> 2025
B59: Equity Share Capital | C59: ='Data Sheet'!G57 -> 1230.88 | D59: ='Data Sheet'!H57 -> 1232.33 | E59: ='Data Sheet'!I57 -> 1242.8 | F59: ='Data Sheet'!J57 -> 1248.47 | G59: ='Data Sheet'!K57 -> 1251.41
B60: Reserves | C60: ='Data Sheet'!G58 -> 59116.46 | D60: ='Data Sheet'!H58 -> 61223.24 | E60: ='Data Sheet'!I58 -> 67912.46 | F60: ='Data Sheet'!J58 -> 73258.53 | G60: ='Data Sheet'!K58 -> 68778.64
B61: Borrowings | C61: ='Data Sheet'!G59 -> 270.83 | D61: ='Data Sheet'!H59 -> 249.44 | E61: ='Data Sheet'!I59 -> 306.04 | F61: ='Data Sheet'!J59 -> 303.43 | G61: ='Data Sheet'!K59 -> 284.54
B62: Other Liabilities | C62: ='Data Sheet'!G60 -> 13142.59 | D62: ='Data Sheet'!H60 -> 14491.01 | E62: ='Data Sheet'!I60 -> 16369.66 | F62: ='Data Sheet'!J60 -> 16943.54 | G62: ='Data Sheet'!K60 -> 17688.11
B63: Total | C63: =SUM(C59:C62) -> 73760.76 | D63: =SUM(D59:D62) -> 77196.02 | E63: =SUM(E59:E62) -> 85830.96 | F63: =SUM(F59:F62) -> 91753.97 | G63: =SUM(G59:G62) -> 88002.7
B64: Net Block | C64: ='Data Sheet'!G62 -> 23298.48 | D64: ='Data Sheet'!H62 -> 24231.59 | E64: ='Data Sheet'!I62 -> 25851.27 | F64: ='Data Sheet'!J62 -> 27820.22 | G64: ='Data Sheet'!K62 -> 21954.85
B65: Capital Work in Progress | C65: ='Data Sheet'!G63 -> 4011.29 | D65: ='Data Sheet'!H63 -> 3225.54 | E65: ='Data Sheet'!I63 -> 3003.3 | F65: ='Data Sheet'!J63 -> 2860.78 | G65: ='Data Sheet'!K63 -> 1090.91
B66: Investments | C66: ='Data Sheet'!G64 -> 24870.87 | D66: ='Data Sheet'!H64 -> 24841.01 | E66: ='Data Sheet'!I64 -> 29415.02 | F66: ='Data Sheet'!J64 -> 31114.02 | G66: ='Data Sheet'!K64 -> 34719.82
B67: Receivables | C67: ='Data Sheet'!G67 -> 2501.7 | D67: ='Data Sheet'!H67 -> 2461.9 | E67: ='Data Sheet'!I67 -> 2956.17 | F67: ='Data Sheet'!J67 -> 4025.82 | G67: ='Data Sheet'!K67 -> 4719.67
B68: Inventory | C68: ='Data Sheet'!G68 -> 10397.16 | D68: ='Data Sheet'!H68 -> 10864.15 | E68: ='Data Sheet'!I68 -> 11771.16 | F68: ='Data Sheet'!J68 -> 14152.88 | G68: ='Data Sheet'!K68 -> 15637.56
B69: Cash & Bank | C69: ='Data Sheet'!G69 -> 4659.02 | D69: ='Data Sheet'!H69 -> 4654.42 | E69: ='Data Sheet'!I69 -> 4880.19 | F69: ='Data Sheet'!J69 -> 7217.68 | G69: ='Data Sheet'!K69 -> 4012.36
B70: Other Assets | C70: ='Data Sheet'!G65-SUM('Data Sheet'!G67:G69) -> 4022.24 | D70: ='Data Sheet'!H65-SUM('Data Sheet'!H67:H69) -> 6917.41 | E70: ='Data Sheet'!I65-SUM('Data Sheet'!I67:I69) -> 7953.85 | F70: ='Data Sheet'!J65-SUM('Data Sheet'!J67:J69) -> 4562.57 | G70: ='Data Sheet'!K65-SUM('Data Sheet'!K67:K69) -> 5867.53
B71: Total | C71: =SUM(C64:C70) -> 73760.76 | D71: =SUM(D64:D70) -> 77196.02 | E71: =SUM(E64:E70) -> 85830.96 | F71: =SUM(F64:F70) -> 91753.97 | G71: =SUM(G64:G70) -> 88002.7
B73: Revenue Projections & Growth Assumptions
B74: Year | C74: FY26E | D74: FY27E | E74: FY28E | F74: FY29E | G74: FY30E
B75: Revenue Growth % | C75: {=CHOOSE(D77,C78:G78,C79:G79,C80:G80)} -> 0.2 | D75: 0.18 | E75: 0.16 | F75: 0.14 | G75: 0.12
B76: Revenue (in Crs.) | C76: =G33*(1+C75) -> 90388.008 | D76: =C76*(1+D75) -> 106657.85 | E76: =D76*(1+E75) -> 123723.11 | F76: =E76*(1+F75) -> 141044.34 | G76: =F76*(1+G75) -> 157969.66
B77: Chosen Scenario: | C77: Base Case | D77: =MATCH(C77,B78:B80) -> 1
B78: Base Case | C78: =C20 -> 0.2 | D78: =C78-Taper_rate -> 0.18 | E78: =D78-Taper_rate -> 0.16 | F78: =E78-Taper_rate -> 0.14 | G78: =F78-Taper_rate -> 0.12
B79: Best Case | C79: =C78+5% -> 0.25 | D79: =C79-Taper_rate -> 0.23 | E79: =D79-Taper_rate -> 0.21 | F79: =E79-Taper_rate -> 0.19 | G79: =F79-Taper_rate -> 0.17
B80: Worst Case | C80: =C78-5% -> 0.15 | D80: =C80-Taper_rate -> 0.13 | E80: =D80-Taper_rate -> 0.11 | F80: =E80-Taper_rate -> 0.09 | G80: =F80-Taper_rate -> 0.07
B82: Free Cash Flow Projections (₹ Crores)
B83: Particulars | C83: FY26E | D83: FY27E | E83: FY28E | F83: FY29E | G83: FY30E
B84: Revenue | C84: =C76 -> 90388.008 | D84: =D76 -> 106657.85 | E84: =E76 -> 123723.11 | F84: =F76 -> 141044.34 | G84: =G76 -> 157969.66
B85: EBITDA Margin % | C85: =D42 -> 0.34006606 | D85: =C85 -> 0.34006606 | E85: =D85 -> 0.34006606 | F85: =E85 -> 0.34006606 | G85: =F85 -> 0.34006606
B86: EBITDA | C86: =C85*C84 -> 30737.894 | D86: =D85*D84 -> 36270.715 | E86: =E85*E84 -> 42074.029 | F86: =F85*F84 -> 47964.394 | G86: =G85*G84 -> 53720.121
B87: Less: Depreciation | C87: =C84*AVERAGE(C44:G44) -> 2380.5672 | D87: =D84*AVERAGE(D44:H44) -> 2620.5318 | E87: =E84*AVERAGE(E44:I44) -> 2874.9719 | F87: =F84*AVERAGE(F44:J44) -> 3117.3152 | G87: =G84*AVERAGE(G44:K44) -> 3452.6962
B88: EBIT | C88: =C86-C87 -> 28357.327 | D88: =D86-D87 -> 33650.183 | E88: =E86-E87 -> 39199.057 | F88: =F86-F87 -> 44847.078 | G88: =G86-G87 -> 50267.425
B89: Less: Tax | C89: =C88*Tax_Rate -> 7089.3317 | D89: =D88*Tax_Rate -> 8412.5458 | E89: =E88*Tax_Rate -> 9799.7644 | F89: =F88*Tax_Rate -> 11211.77 | G89: =G88*Tax_Rate -> 12566.856
B90: NOPAT | C90: =C88-C89 -> 21267.995 | D90: =D88-D89 -> 25237.637 | E90: =E88-E89 -> 29399.293 | F90: =F88-F89 -> 33635.309 | G90: =G88-G89 -> 37700.568
B91: Add: Depreciation | C91: =C87 -> 2380.5672 | D91: =D87 -> 2620.5318 | E91: =E87 -> 2874.9719 | F91: =F87 -> 3117.3152 | G91: =G87 -> 3452.6962
B92: Less: Reinvestment | C92: =-C90*$C$26 -> -6380.3985 | D92: =-D90*$C$26 -> -7571.2912 | E92: =-E90*$C$26 -> -8819.7879 | F92: =-F90*$C$26 -> -10090.593 | G92: =-G90*$C$26 -> -11310.171
B93: Free Cash Flow to Firm | C93: =SUM(C84:C92) -> 176221.63 | D93: =SUM(D84:D92) -> 207899.04 | E93: =SUM(E84:E92) -> 241125.75 | F93: =SUM(F84:F92) -> 274847.27 | G93: =SUM(G84:G92) -> 307820.19
B95: WACC Calculation
B97: Target Capital Structure
B98: Proportion of Debt | C98: ='Comps '!F25 -> 0.0081662893
B99: Proportion of Equity | C99: =1-C98 -> 0.99183371
B100: Current Capital Structure
B101: Market Cap | C101: ='Comps '!E14 -> 501275.87
B102: Total Debt | C102: ='Comps '!J14 -> 362.97
B103: Debt / Equity | C103: =C102/C101 -> 0.0007240923
B104: Cost of Debt
B105: Pre-Tax Cost of Debt | C105: =C27 -> 0.08
B106: Tax Rate | C106: =Tax_Rate -> 0.25
B107: After-Tax Cost of Debt | C107: =C105*(1-C106) -> 0.06
B108: Cost of Equity
B109: Risk Free Rate | C109: =C23 -> 0.065
B110: Equity Risk Premium | C110: =C24 -> 0.055
B111: Levered Equity Beta | C111: ='Comps '!H25 -> 0.745
B112: Cost of Equity | C112: =C109+C111*C110 -> 0.105975
...

Sheet Comps 
B3: Financial Modelling
B7: Comps Data
B9: Company | C9: Ticker | D9: Price | E9: Market Cap | F9: Sales | G9: EBITDA | H9: Net Income | I9: Beta | J9: Total Debt | K9: Cash & Cash Equivalents | L9: P/E
B10: ='comps data'!C4 -> Hind. Unilever | D10: ='comps data'!D4 -> 2260.6 | E10: ='comps data'!F4 -> 531148.6 | F10: ='comps data'!E4 -> 64243 | G10: ='comps data'!H4 -> 15860 | H10: ='comps data'!I4 -> 10671 | I10: 0.48 | J10: ='comps data'!J4 -> 1775 | K10: ='comps data'!K4 -> 7554 | L10: ='comps data'!G4 -> 50.21
B11: ='comps data'!C5 -> Nestle India | D11: ='comps data'!D5 -> 1238.3 | E11: ='comps data'!F5 -> 238783.16 | F11: ='comps data'!E5 -> 21023.38 | G11: ='comps data'!H5 -> 4830.19 | H11: ='comps data'!I5 -> 3314.5 | I11: 0.92 | J11: ='comps data'!J5 -> 476.85 | K11: ='comps data'!K5 -> 95.65 | L11: ='comps data'!G5 -> 79.75
B12: ='comps data'!C6 -> Varun Beverages | D12: ='comps data'!D6 -> 479.95 | E12: ='comps data'!F6 -> 162318.55 | F12: ='comps data'!E6 -> 21169.75 | G12: ='comps data'!H6 -> 4933.96 | H12: ='comps data'!I6 -> 2634.28 | I12: 0.73 | J12: ='comps data'!J6 -> 2138.25 | K12: ='comps data'!K6 -> 2450.05 | L12: ='comps data'!G6 -> 54.66
B13: ='comps data'!C7 -> Britannia Inds. | D13: ='comps data'!D7 -> 5915.5 | E13: ='comps data'!F7 -> 142485.64 | F13: ='comps data'!E7 -> 18487.65 | G13: ='comps data'!H7 -> 3402.26 | H13: ='comps data'!I7 -> 2177.86 | I13: 0.76 | J13: ='comps data'!J7 -> 2196.3 | K13: ='comps data'!K7 -> 312.48 | L13: ='comps data'!G7 -> 61.5
B14: ='comps data'!C8 -> ITC | D14: ='comps data'!D8 -> 400.1 | E14: ='comps data'!F8 -> 501275.87 | F14: ='comps data'!E8 -> 78551.59 | G14: ='comps data'!H8 -> 28479.56 | H14: ='comps data'!I8 -> 35052.48 | I14: 0.59 | J14: ='comps data'!J8 -> 362.97 | K14: ='comps data'!K8 -> 4012.36 | L14: ='comps data'!G8 -> 24.85
B16: Industry Beta
C18: Equity | D18: Total | E18: Debt/ | F18: Debt/ | G18: Tax | H18: Levered | I18: Unlevered
B19: Company Name | C19: Value | D19: Debt | E19: Equity | F19: Capital | G19: Rate % | H19: Beta | I19: Beta
B20: =B10 -> Hind. Unilever | C20: =E10 -> 531148.6 | D20: =J10 -> 1775 | E20: =D20/C20 -> 0.0033418143 | F20: =D20/(C20+D20) -> 0.0033306838 | G20: =Tax_Rate -> 0.25 | H20: =I10 -> 0.48 | I20: =H20/(1+E20*(1-Tax_Rate)) -> 0.47879995
B21: =B11 -> Nestle India | C21: =E11 -> 238783.16 | D21: =J11 -> 476.85 | E21: =D21/C21 -> 0.0019970001 | F21: =D21/(C21+D21) -> 0.0019930201 | G21: =Tax_Rate -> 0.25 | H21: =I11 -> 0.92 | I21: =H21/(1+E21*(1-Tax_Rate)) -> 0.91862413
B22: =B12 -> Varun Beverages | C22: =E12 -> 162318.55 | D22: =J12 -> 2138.25 | E22: =D22/C22 -> 0.013173171 | F22: =D22/(C22+D22) -> 0.013001895 | G22: =Tax_Rate -> 0.25 | H22: =I12 -> 0.73 | I22: =H22/(1+E22*(1-Tax_Rate)) -> 0.72285825
B23: =B13 -> Britannia Inds. | C23: =E13 -> 142485.64 | D23: =J13 -> 2196.3 | E23: =D23/C23 -> 0.015414185 | F23: =D23/(C23+D23) -> 0.015180195 | G23: =Tax_Rate -> 0.25 | H23: =I13 -> 0.76 | I23: =H23/(1+E23*(1-Tax_Rate)) -> 0.75131433
B24: Average | C24: =AVERAGE(C20:C23) -> 268683.99 | D24: =AVERAGE(D20:D23) -> 1646.6 | E24: =AVERAGE(E20:E23) -> 0.0084815426 | F24: =AVERAGE(F20:F23) -> 0.0083764483 | G24: =AVERAGE(G20:G23) -> 0.25 | H24: =AVERAGE(H20:H23) -> 0.7225 | I24: =AVERAGE(I20:I23) -> 0.71789917
B25: Median | C25: =MEDIAN(C20:C23) -> 200550.85 | D25: =MEDIAN(D20:D23) -> 1956.625 | E25: =MEDIAN(E20:E23) -> 0.0082574926 | F25: =MEDIAN(F20:F23) -> 0.0081662893 | G25: =MEDIAN(G20:G23) -> 0.25 | H25: =MEDIAN(H20:H23) -> 0.745 | I25: =MEDIAN(I20:I23) -> 0.73708629
B27: Comparable Companies Analysis
D29: Market Data | J29: Financial Data | M29: Valuation
D30: Price | E30: Shares | F30: Market Cap | G30: Debt | H30: Cash | I30: EV | J30: Sales | K30: EBITDA | L30: Earnings | M30: EV/Sales | N30: EV/EBITDA | O30: P/E
B31: Company Name | C31: Ticker | D31: (₹/share) | E31: In Cr. | F31: In Cr. | H31: & Equivalents | I31: In Cr. | J31: In Cr. | K31: In Cr. | L31: In Cr. | M31: x | N31: x | O31: x
B32: =B20 -> Hind. Unilever | D32: =D10 -> 2260.6 | E32: =F32/D32 -> 234.95913 | F32: =E10 -> 531148.6 | G32: =J10 -> 1775 | H32: =+K10 -> 7554 | I32: =F32+G32-H32 -> 525369.6 | J32: =F10 -> 64243 | K32: =G10 -> 15860 | L32: =H10 -> 10671 | M32: =I32/J32 -> 8.1778497 | N32: =I32/K32 -> 33.125448 | O32: =F32/L32 -> 49.77496
B33: =B21 -> Nestle India | D33: =D11 -> 1238.3 | E33: =F33/D33 -> 192.83143 | F33: =E11 -> 238783.16 | G33: =J11 -> 476.85 | H33: =+K11 -> 95.65 | I33: =F33+G33-H33 -> 239164.36 | J33: =F11 -> 21023.38 | K33: =G11 -> 4830.19 | L33: =H11 -> 3314.5 | M33: =I33/J33 -> 11.376114 | N33: =I33/K33 -> 49.514483 | O33: =F33/L33 -> 72.041985
B34: =B22 -> Varun Beverages | D34: =D12 -> 479.95 | E34: =F34/D34 -> 338.19887 | F34: =E12 -> 162318.55 | G34: =J12 -> 2138.25 | H34: =+K12 -> 2450.05 | I34: =F34+G34-H34 -> 162006.75 | J34: =F12 -> 21169.75 | K34: =G12 -> 4933.96 | L34: =H12 -> 2634.28 | M34: =I34/J34 -> 7.6527474 | N34: =I34/K34 -> 32.835035 | O34: =F34/L34 -> 61.617804
B35: =B23 -> Britannia Inds. | D35: =D13 -> 5915.5 | E35: =F35/D35 -> 24.08683 | F35: =E13 -> 142485.64 | G35: =J13 -> 2196.3 | H35: =+K13 -> 312.48 | I35: =F35+G35-H35 -> 144369.46 | J35: =F13 -> 18487.65 | K35: =G13 -> 3402.26 | L35: =H13 -> 2177.86 | M35: =I35/J35 -> 7.8089676 | N35: =I35/K35 -> 42.4334 | O35: =F35/L35 -> 65.424609
B37: Average | M37: =AVERAGE(M32:M35) -> 8.7539196 | N37: =AVERAGE(N32:N35) -> 39.477091 | O37: =AVERAGE(O32:O35) -> 62.21484
B38: Median | M38: =MEDIAN(M32:M35) -> 7.9934087 | N38: =MEDIAN(N32:N35) -> 37.779424 | O38: =MEDIAN(O32:O35) -> 63.521207
B40: =B14 -> ITC | D40: =D14 -> 400.1 | E40: =F40/D40 -> 1252.8765 | F40: =E14 -> 501275.87 | G40: =J14 -> 362.97 | H40: =K14 -> 4012.36 | I40: =F40+G40-H40 -> 497626.48 | J40: =F14 -> 78551.59 | K40: =G14 -> 28479.56 | L40: =H14 -> 35052.48 | M40: =I40/J40 -> 6.3350275 | N40: =I40/K40 -> 17.47311 | O40: =F40/L40 -> 14.300725
B42: Metric | C42: Comps | D42: EV | E42: Net Debt | F42: Equity Value | G42: Shares | H42: Share Price
B43: EV/Sales | C43: =M38 -> 7.9934087 | D43: =C43*J40 -> 627894.96 | E43: =$G$40 -> 362.97 | F43: =D43-E43 -> 627531.99 | G43: =$E$40 -> 1252.8765 | H43: =F43/G43 -> 500.873
B44: EV/Ebitda | C44: =N38 -> 37.779424 | D44: =C44*K40 -> 1075941.4 | E44: =$G$40 -> 362.97 | F44: =D44-E44 -> 1075578.4 | G44: =$E$40 -> 1252.8765 | H44: =F44/G44 -> 858.4872
B45: P/E | C45: =O38 -> 63.521207 | D45: =F45+E45 -> 2226938.8 | E45: =$G$40 -> 362.97 | F45: =C45*L40 -> 2226575.8 | G45: =$E$40 -> 1252.8765 | H45: =F45/G45 -> 1777.1711
B49: Findings
B51: Why Comps data is important?
B52: This analysis compares ITC with similar FMCG companies (HUL, Nestle, Varun Beverages, Britannia) to see whether ITC’s stock is cheap or expensive versus peers.
B54: *Peer valuation vs ITC (simple comparison)
B56: Peers (Median):
B57: EV/Sales: 8.0x
B58: EV/EBITDA: 37.8x
B59: P/E: 63.5x
B61: ITC today:
B62: EV/Sales: 6.3x
B63: EV/EBITDA: 17.5x
B64: P/E: 14.3x
... B77: ~Compared to other FMCG companies, ITC looks undervalued despite strong profits and a solid balance sheet.

Sheet Data Sheet
A1: COMPANY NAME | B1: ITC LTD | E1: =IF(B2<>B3, "A NEW VERSION OF THE WORKSHEET IS AVAILABLE", "")
A2: LATEST VERSION | B2: 2.1 | E2: PLEASE DO NOT MAKE ANY CHANGES TO THIS SHEET
A3: CURRENT VERSION | B3: 2.1
A5: META
A6: Number of shares | B6: =IF(B9>0, B9/B8, 0) -> 1252.8765
A7: Face Value | B7: 1
A8: Current Price | B8: 400.1
A9: Market Capitalization | B9: 501275.87
A15: PROFIT & LOSS
A16: Report Date | B16: 42460 | C16: 42825 | D16: 43190 | E16: 43555 | F16: 43921 | G16: 44286 | H16: 44651 | I16: 45016 | J16: 45382 | K16: 45747
A17: Sales | B17: 39192.1 | C17: 42767.6 | D17: 43448.94 | E17: 48339.58 | F17: 49387.7 | G17: 49257.45 | H17: 60644.54 | I17: 70919.03 | J17: 67931.94 | K17: 75323.34
A18: Raw Material Cost | B18: 13763.88 | C18: 15456.59 | D18: 14827.72 | E18: 17623.52 | F18: 18048.6 | G18: 20776.71 | H18: 27071.07 | I18: 29364.36 | J18: 27348.57 | K18: 32704.37
A19: Change in Inventory | B19: 195.38 | C19: -592.57 | D19: -1027.76 | E19: 203.19 | F19: 703.13 | G19: 645.27 | H19: 686 | I19: 358.59 | J19: 367.77 | K19: 725.65
A20: Power and Fuel | B20: 571.88 | C20: 584.33 | D20: 653.5 | E20: 746.73 | F20: 780.85 | G20: 699.56 | H20: 889.77 | I20: 1232.34 | J20: 952.9 | K20: 975.35
A21: Other Mfr. Exp | B21: 1581.59 | C21: 1683.9 | D21: 1697.62 | E21: 1871.01 | F21: 1908.29 | G21: 1587.18 | H21: 1887.67 | I21: 2327.8 | J21: 2183.76 | K21: 2345.36
A22: Employee Cost | B22: 3440.97 | C22: 3631.73 | D22: 3760.9 | E22: 4177.88 | F22: 4295.79 | G22: 4463.33 | H22: 4890.55 | I22: 5736.22 | J22: 5548.53 | K22: 6169.78
A23: Selling and admin | B23: 4261.78 | C23: 4179.74 | D23: 3954.87 | E23: 4546.39 | F23: 4488.63 | G23: 4236.77 | H23: 4858.38 | I23: 5604.08 | J23: 5312.45 | K23: 5793.29
A24: Other Expenses | B24: 1235.89 | C24: 1169.23 | D24: 1005.98 | E24: 1039.85 | F24: 1225.13 | G24: 1074.39 | H24: 1109.95 | I24: 1308.56 | J24: 1765.97 | K24: 2221.39
A25: Other Income | B25: 1483.11 | C25: 1758.63 | D25: 2239.81 | E25: 2080.44 | F25: 2417.32 | G25: 2576.95 | H25: 1909.72 | I25: 2097.64 | J25: 3330.45 | K25: 17794.88
A26: Depreciation | B26: 1077.4 | C26: 1152.79 | D26: 1236.28 | E26: 1396.61 | F26: 1644.91 | G26: 1645.59 | H26: 1732.41 | I26: 1809.01 | J26: 1518.05 | K26: 1646.32
A27: Interest | B27: 78.13 | C27: 49.03 | D27: 115.01 | E27: 71.4 | F27: 81.38 | G27: 57.97 | H27: 59.99 | I27: 77.77 | J27: 39.11 | K27: 45.06
... A31: Dividend Amount | B31: 6840.12 | C31: 5770.02 | D31: 6285.21 | E31: 7048.7 | F31: 12476.58 | G31: 13231.96 | H31: 14171.8 | I31: 19263.4 | J31: 17166.46 | K31: 17957.73
A40: Quarters
A41: Report Date | B41: 45107 | C41: 45199 | D41: 45291 | E41: 45382 | F41: 45473 | G41: 45565 | H41: 45657 | I41: 45747 | J41: 45838 | K41: 45930
A42: Sales | B42: 17164.46 | C42: 17774.47 | D42: 17195.24 | E42: 17037.8 | F42: 17777.81 | G42: 19990.36 | H42: 18790.17 | I42: 18765 | J42: 21494.79 | K42: 19501.63
A43: Expenses | B43: 10494.39 | C43: 11320.23 | D43: 10985.01 | E43: 10735.73 | F43: 11232.97 | G43: 13438.28 | H43: 12428.27 | I43: 12245.61 | J43: 14678.32 | K43: 12806.94
A44: Other Income | B44: 722.3 | C44: 673.5 | D44: 820.26 | E44: 868 | F44: 771.13 | G44: 690.31 | H44: 803.4 | I44: 15391.28 | J44: 750.97 | K44: 738.84
A45: Depreciation | B45: 442.46 | C45: 453.04 | D45: 384.04 | E45: 385.09 | F45: 403.13 | G45: 416.18 | H45: 415.98 | I45: 411.03 | J45: 422.96 | K45: 434.8
A46: Interest | B46: 9.9 | C46: 9.87 | D46: 11.94 | E46: 10.72 | F46: 9.6 | G46: 14.73 | H46: 9.82 | I46: 10.91 | J46: 16.47 | K46: 20.05
A47: Profit before tax | B47: 6940.01 | C47: 6664.83 | D47: 6634.51 | E47: 6774.26 | F47: 6903.24 | G47: 6811.48 | H47: 6739.5 | I47: 21488.73 | J47: 7128.01 | K47: 6978.68
A48: Tax | B48: 1759.89 | C48: 1700.31 | D48: 1227.99 | E48: 1583.55 | F48: 1726.25 | G48: 1757.05 | H48: 1726.32 | I48: 1680.85 | J48: 1784.6 | K48: 1792.13
A49: Net profit | B49: 5104.93 | C49: 4898.07 | D49: 5335.23 | E49: 5120.55 | F49: 5091.59 | G49: 4992.87 | H49: 4934.8 | I49: 19727.37 | J49: 5244.2 | K49: 5126.11
A50: Operating Profit | B50: 6670.07 | C50: 6454.24 | D50: 6210.23 | E50: 6302.07 | F50: 6544.84 | G50: 6552.08 | H50: 6361.9 | I50: 6519.39 | J50: 6816.47 | K50: 6694.69
A55: BALANCE SHEET
A56: Report Date | B56: 42460 | C56: 42825 | D56: 43190 | E56: 43555 | F56: 43921 | G56: 44286 | H56: 44651 | I56: 45016 | J56: 45382 | K56: 45747
A57: Equity Share Capital | B57: 804.72 | C57: 1214.74 | D57: 1220.43 | E57: 1225.86 | F57: 1229.22 | G57: 1230.88 | H57: 1232.33 | I57: 1242.8 | J57: 1248.47 | K57: 1251.41
A58: Reserves | B58: 41874.8 | C58: 45198.19 | D58: 51289.68 | E58: 57915.01 | F58: 64044.04 | G58: 59116.46 | H58: 61223.24 | I58: 67912.46 | J58: 73258.53 | K58: 68778.64
A59: Borrowings | B59: 83.78 | C59: 45.72 | D59: 35.92 | E59: 13.44 | F59: 277.45 | G59: 270.83 | H59: 249.44 | I59: 306.04 | J59: 303.43 | K59: 284.54
A60: Other Liabilities | B60: 8888.04 | C60: 9439.67 | D60: 11694.85 | E60: 12584.73 | F60: 11760.04 | G60: 13142.59 | H60: 14491.01 | I60: 16369.66 | J60: 16943.54 | K60: 17688.11
A61: Total | B61: 51651.34 | C61: 55898.32 | D61: 64240.88 | E61: 71739.04 | F61: 77310.75 | G61: 73760.76 | H61: 77196.02 | I61: 85830.96 | J61: 91753.97 | K61: 88002.7
A62: Net Block | B62: 15106.63 | C62: 15893.48 | D62: 16523.96 | E62: 19374.19 | F62: 21713.34 | G62: 23298.48 | H62: 24231.59 | I62: 25851.27 | J62: 27820.22 | K62: 21954.85
A63: Capital Work in Progress | B63: 2559.72 | C63: 3729.89 | D63: 5508.33 | E63: 4136.42 | F63: 3256.46 | G63: 4011.29 | H63: 3225.54 | I63: 3003.3 | J63: 2860.78 | K63: 1090.91
A64: Investments | B64: 11747.59 | C64: 17581.38 | D64: 22052.86 | E64: 25043.49 | F64: 28663.35 | G64: 24870.87 | H64: 24841.01 | I64: 29415.02 | J64: 31114.02 | K64: 34719.82
A65: Other Assets | B65: 22237.4 | C65: 18693.57 | D65: 20155.73 | E65: 23184.94 | F65: 23677.6 | G65: 21580.12 | H65: 24897.88 | I65: 27561.37 | J65: 29958.95 | K65: 30237.12
A66: Total | B66: 51651.34 | C66: 55898.32 | D66: 64240.88 | E66: 71739.04 | F66: 77310.75 | G66: 73760.76 | H66: 77196.02 | I66: 85830.96 | J66: 91753.97 | K66: 88002.7
A67: Receivables | B67: 1917.18 | C67: 2474.29 | D67: 2682.29 | E67: 4035.28 | F67: 2562.48 | G67: 2501.7 | H67: 2461.9 | I67: 2956.17 | J67: 4025.82 | K67: 4719.67
... A70: No. of Equity Shares | B70: 8047206991 | C70: 12147383071 | D70: 12204294911 | E70: 12258631601 | F70: 12292231241 | G70: 12308844231 | H70: 12323255931 | I70: 12428017741 | J70: 12484700000 | K70: 12514119781
A71: New Bonus Shares | C71: 4026657100
A72: Face value | B72: 1 | C72: 1 | D72: 1 | E72: 1 | F72: 1 | G72: 1 | H72: 1 | I72: 1 | J72: 1 | K72: 1
A75: change in inventory | I75: =SUM(H67:H68)-SUM(I67:I68) -> -1401.28 | J75: =SUM(I67:I68)-SUM(J67:J68) -> -3451.37 | K75: =SUM(J67:J68)-SUM(K67:K68) -> -2178.53
A76: total | I76: =I75+I83 -> -7133.57 | J76: =J75+J83 -> -1888.6 | K76: =K75+K83 -> -2742.37
A77: nopat | I77: ='DCF Valuation '!E45*(1+Tax_Rate) -> 29869.062 | J77: ='DCF Valuation '!F45*(1+Tax_Rate) -> 29586.85 | K77: ='DCF Valuation '!G45*(1+Tax_Rate) -> 30241.412
I78: =-I76/I77 -> 0.23882805 | J78: =-J76/J77 -> 0.063832412 | K78: =-K76/K77 -> 0.090682603
A80: CASH FLOW:
A81: Report Date | B81: 42460 | C81: 42825 | D81: 43190 | E81: 43555 | F81: 43921 | G81: 44286 | H81: 44651 | I81: 45016 | J81: 45382 | K81: 45747
A82: Cash from Operating Activity | B82: 9799.04 | C82: 10627.31 | D82: 13169.4 | E82: 12583.41 | F82: 14689.66 | G82: 12526.97 | H82: 15775.51 | I82: 18877.55 | J82: 17178.86 | K82: 17627.04
A83: Cash from Investing Activity | B83: -3920.73 | C83: -3250.93 | D83: -7113.89 | E83: -5545.68 | F83: -6174.02 | G83: 5739.98 | H83: -2238.49 | I83: -5732.29 | J83: 1562.77 | K83: -563.84
A84: Cash from Financing Activity | B84: -5612.52 | C84: -7301.03 | D84: -6221.13 | E84: -6868.64 | F84: -8181.48 | G84: -18633.83 | H84: -13580.5 | I84: -13006.03 | J84: -18550.96 | K84: -17037.4
A85: Net Cash Flow | B85: 265.79 | C85: 75.35 | D85: -165.62 | E85: 169.09 | F85: 334.16 | G85: -366.88 | H85: -43.48 | I85: 139.23 | J85: 190.67 | K85: 25.8
A90: PRICE: | B90: 205.13 | C90: 262.75 | D90: 239.5 | E90: 278.64 | F90: 160.95 | G90: 204.82 | H90: 234.96 | I90: 359.49 | J90: 401.53 | K90: 409.75
A92: DERIVED:
A93: Adjusted Equity Shares in Cr | B93: 1207.08 | C93: 1214.74 | D93: 1220.43 | E93: 1225.86 | F93: 1229.22 | G93: 1230.88 | H93: 1232.33 | I93: 1242.8 | J93: 1248.47 | K93: 1251.41

Sheet comps data
B2: No. | C2: Name | D2: CMP Rs. | E2: Sales Rs.Cr. | F2: Mar Cap Rs.Cr. | G2: P/E | H2: EBIDT Ann Rs.Cr. | I2: NP Ann Rs.Cr. | J2: Debt Rs.Cr. | K2: Cash End Rs.Cr.
B4: 1 | C4: Hind. Unilever | D4: 2260.6 | E4: 64243 | F4: 531148.6 | G4: 50.21 | H4: 15860 | I4: 10671 | J4: 1775 | K4: 7554
B5: 3 | C5: Nestle India | D5: 1238.3 | E5: 21023.38 | F5: 238783.16 | G5: 79.75 | H5: 4830.19 | I5: 3314.5 | J5: 476.85 | K5: 95.65
B6: 4 | C6: Varun Beverages | D6: 479.95 | E6: 21169.75 | F6: 162318.55 | G6: 54.66 | H6: 4933.96 | I6: 2634.28 | J6: 2138.25 | K6: 2450.05
B7: 5 | C7: Britannia Inds. | D7: 5915.5 | E7: 18487.65 | F7: 142485.64 | G7: 61.5 | H7: 3402.26 | I7: 2177.86 | J7: 2196.3 | K7: 312.48
B8: 2 | C8: ITC | D8: 400.1 | E8: 78551.59 | F8: 501275.87 | G8: 24.85 | H8: 28479.56 | I8: 35052.48 | J8: 362.97 | K8: 4012.36
